[{"T": {"quote": {"03/19/2021": {"value": "29.76", "Market Cap": "212.441B", "Beta (5Y Monthly)": "0.73", "PE Ratio (TTM)": "N/A", "EPS (TTM)": "-0.75", "Earnings Date": "Apr 22, 2021", "Forward Dividend & Yield": "2.08 (6.90%)", "Ex-Dividend Date": "Jan 08, 2021", "1y Target Est": "29.55"}}, "fin": {"TTM": {"Duration": "TTM", "Total Revenue": "171,760,000", "Cost of Revenue": "79,920,000", "Gross Profit": "91,840,000", "Operating Expense": "66,555,000", "Operating Income": "25,285,000", "Net Non Operating Interest Income Expense": "-7,925,000", "Other Income Expense": "-20,216,000", "Pretax Income": "-2,856,000", "Tax Provision": "965,000", "Net Income Common Stockholders": "-5,369,000", "Average Dilution Earnings": "23,000", "Diluted NI Available to Com Stockholders": "-5,346,000", "Basic EPS": "-", "Diluted EPS": "-", "Basic Average Shares": "-", "Diluted Average Shares": "-", "Total Operating Income as Reported": "6,405,000", "Total Expenses": "146,475,000", "Net Income from Continuing & Discontinued Operation": "-5,176,000", "Normalized Income": "8,606,400", "Interest Expense": "7,925,000", "Net Interest Income": "-7,925,000", "EBIT": "5,069,000", "EBITDA": "33,585,000", "Reconciled Cost of Revenue": "79,920,000", "Reconciled Depreciation": "28,516,000", "Net Income from Continuing Operation Net Minority Interest": "-5,176,000", "Total Unusual Items Excluding Goodwill": "-18,880,000", "Total Unusual Items": "-18,880,000", "Normalized EBITDA": "52,465,000", "Tax Rate for Calcs": "0", "Tax Effect of Unusual Items": "-5,097,600"}, "12/31/2020": {"Duration": "12/31/2020", "Total Revenue": "171,760,000", "Cost of Revenue": "79,920,000", "Gross Profit": "91,840,000", "Operating Expense": "66,555,000", "Operating Income": "25,285,000", "Net Non Operating Interest Income Expense": "-7,925,000", "Other Income Expense": "-20,216,000", "Pretax Income": "-2,856,000", "Tax Provision": "965,000", "Net Income Common Stockholders": "-5,369,000", "Average Dilution Earnings": "23,000", "Diluted NI Available to Com Stockholders": "-5,346,000", "Basic EPS": "-", "Diluted EPS": "-", "Basic Average Shares": "-", "Diluted Average Shares": "-", "Total Operating Income as Reported": "6,405,000", "Total Expenses": "146,475,000", "Net Income from Continuing & Discontinued Operation": "-5,176,000", "Normalized Income": "8,606,400", "Interest Expense": "7,925,000", "Net Interest Income": "-7,925,000", "EBIT": "5,069,000", "EBITDA": "-", "Reconciled Cost of Revenue": "79,920,000", "Reconciled Depreciation": "28,516,000", "Net Income from Continuing Operation Net Minority Interest": "-5,176,000", "Total Unusual Items Excluding Goodwill": "-18,880,000", "Total Unusual Items": "-18,880,000", "Normalized EBITDA": "52,465,000", "Tax Rate for Calcs": "0", "Tax Effect of Unusual Items": "-5,097,600"}, "12/31/2019": {"Duration": "12/31/2019", "Total Revenue": "181,193,000", "Cost of Revenue": "84,141,000", "Gross Profit": "97,052,000", "Operating Expense": "67,639,000", "Operating Income": "29,413,000", "Net Non Operating Interest Income Expense": "-8,422,000", "Other Income Expense": "-2,523,000", "Pretax Income": "18,468,000", "Tax Provision": "3,493,000", "Net Income Common Stockholders": "13,900,000", "Average Dilution Earnings": "21,000", "Diluted NI Available to Com Stockholders": "13,921,000", "Basic EPS": "1.90", "Diluted EPS": "1.89", "Basic Average Shares": "7,319,000", "Diluted Average Shares": "7,348,000", "Total Operating Income as Reported": "27,955,000", "Total Expenses": "151,780,000", "Net Income from Continuing & Discontinued Operation": "13,903,000", "Normalized Income": "15,085,438", "Interest Expense": "8,422,000", "Net Interest Income": "-8,422,000", "EBIT": "26,890,000", "EBITDA": "-", "Reconciled Cost of Revenue": "84,141,000", "Reconciled Depreciation": "28,217,000", "Net Income from Continuing Operation Net Minority Interest": "13,903,000", "Total Unusual Items Excluding Goodwill": "-1,458,000", "Total Unusual Items": "-1,458,000", "Normalized EBITDA": "56,565,000", "Tax Rate for Calcs": "0", "Tax Effect of Unusual Items": "-275,562"}, "12/31/2018": {"Duration": "12/31/2018", "Total Revenue": "170,756,000", "Cost of Revenue": "79,419,000", "Gross Profit": "91,337,000", "Operating Expense": "65,195,000", "Operating Income": "26,142,000", "Net Non Operating Interest Income Expense": "-7,957,000", "Other Income Expense": "6,688,000", "Pretax Income": "24,873,000", "Tax Provision": "4,920,000", "Net Income Common Stockholders": "19,370,000", "Average Dilution Earnings": "19,000", "Diluted NI Available to Com Stockholders": "19,389,000", "Basic EPS": "2.85", "Diluted EPS": "2.85", "Basic Average Shares": "6,778,000", "Diluted Average Shares": "6,806,000", "Total Operating Income as Reported": "26,096,000", "Total Expenses": "144,614,000", "Net Income from Continuing & Discontinued Operation": "19,370,000", "Normalized Income": "19,406,892", "Interest Expense": "7,957,000", "Net Interest Income": "-7,957,000", "EBIT": "32,830,000", "EBITDA": "-", "Reconciled Cost of Revenue": "79,419,000", "Reconciled Depreciation": "28,430,000", "Net Income from Continuing Operation Net Minority Interest": "19,370,000", "Total Unusual Items Excluding Goodwill": "-46,000", "Total Unusual Items": "-46,000", "Normalized EBITDA": "61,306,000", "Tax Rate for Calcs": "0", "Tax Effect of Unusual Items": "-9,108"}}, "bs": {"12/31/2020": {"Duration": "12/31/2020", "Total Assets": "525,761,000", "Total Liabilities Net Minority Interest": "346,521,000", "Total Equity Gross Minority Interest": "179,240,000", "Total Capitalization": "313,601,000", "Common Stock Equity": "161,673,000", "Capital Lease Obligations": "24,238,000", "Net Tangible Assets": "-119,902,000", "Working Capital": "-11,430,000", "Invested Capital": "316,882,000", "Tangible Book Value": "-119,902,000", "Total Debt": "179,447,000", "Net Debt": "145,469,000", "Share Issued": "7,620,749", "Ordinary Shares Number": "7,125,922", "Preferred Shares Number": "118,000", "Treasury Shares Number": "494,827"}, "12/31/2019": {"Duration": "12/31/2019", "Total Assets": "551,669,000", "Total Liabilities Net Minority Interest": "349,735,000", "Total Equity Gross Minority Interest": "201,934,000", "Total Capitalization": "333,658,000", "Common Stock Equity": "184,221,000", "Capital Lease Obligations": "23,838,000", "Net Tangible Assets": "-119,637,000", "Working Capital": "-14,150,000", "Invested Capital": "345,334,000", "Tangible Book Value": "-119,637,000", "Total Debt": "184,951,000", "Net Debt": "148,983,000", "Share Issued": "7,620,749", "Ordinary Shares Number": "7,254,555", "Preferred Shares Number": "48,000", "Treasury Shares Number": "366,193"}, "12/31/2018": {"Duration": "12/31/2018", "Total Assets": "531,864,000", "Total Liabilities Net Minority Interest": "337,980,000", "Total Equity Gross Minority Interest": "193,884,000", "Total Capitalization": "350,339,000", "Common Stock Equity": "184,089,000", "Capital Lease Obligations": "-", "Net Tangible Assets": "-126,108,000", "Working Capital": "-12,993,000", "Invested Capital": "360,594,000", "Tangible Book Value": "-126,108,000", "Total Debt": "176,505,000", "Net Debt": "171,301,000", "Share Issued": "7,620,749", "Ordinary Shares Number": "7,281,629", "Preferred Shares Number": "-", "Treasury Shares Number": "339,120"}}, "cf": {"TTM": {"Duration": "TTM", "Operating Cash Flow": "43,130,000", "Investing Cash Flow": "-13,548,000", "Financing Cash Flow": "-32,007,000", "End Cash Position": "9,870,000", "Income Tax Paid Supplemental Data": "-", "Interest Paid Supplemental Data": "-", "Capital Expenditure": "-15,675,000", "Issuance of Capital Stock": "5,953,000", "Issuance of Debt": "41,428,000", "Repayment of Debt": "-49,448,000", "Repurchase of Capital Stock": "-5,498,000", "Free Cash Flow": "27,455,000"}, "12/31/2020": {"Duration": "12/31/2020", "Operating Cash Flow": "43,130,000", "Investing Cash Flow": "-13,548,000", "Financing Cash Flow": "-32,007,000", "End Cash Position": "9,870,000", "Income Tax Paid Supplemental Data": "-", "Interest Paid Supplemental Data": "-", "Capital Expenditure": "-15,675,000", "Issuance of Capital Stock": "5,953,000", "Issuance of Debt": "41,428,000", "Repayment of Debt": "-49,448,000", "Repurchase of Capital Stock": "-5,498,000", "Free Cash Flow": "27,455,000"}, "12/31/2019": {"Duration": "12/31/2019", "Operating Cash Flow": "48,668,000", "Investing Cash Flow": "-16,690,000", "Financing Cash Flow": "-25,083,000", "End Cash Position": "12,295,000", "Income Tax Paid Supplemental Data": "-", "Interest Paid Supplemental Data": "-", "Capital Expenditure": "-19,435,000", "Issuance of Capital Stock": "9,671,000", "Issuance of Debt": "21,051,000", "Repayment of Debt": "-34,772,000", "Repurchase of Capital Stock": "-2,417,000", "Free Cash Flow": "29,233,000"}, "12/31/2018": {"Duration": "12/31/2018", "Operating Cash Flow": "43,602,000", "Investing Cash Flow": "-63,145,000", "Financing Cash Flow": "-25,989,000", "End Cash Position": "5,400,000", "Income Tax Paid Supplemental Data": "-", "Interest Paid Supplemental Data": "8,818,000", "Capital Expenditure": "-20,758,000", "Issuance of Capital Stock": "745,000", "Issuance of Debt": "46,773,000", "Repayment of Debt": "-55,562,000", "Repurchase of Capital Stock": "-609,000", "Free Cash Flow": "22,844,000"}}}}, {"ALSK": {"quote": {"03/19/2021": {"value": "3.2600", "Market Cap": "176.376M", "Beta (5Y Monthly)": "1.46", "PE Ratio (TTM)": "N/A", "EPS (TTM)": "-0.0200", "Earnings Date": "May 04, 2021 - May 10, 2021", "Forward Dividend & Yield": "N/A (N/A)", "Ex-Dividend Date": "Apr 17, 2020", "1y Target Est": "N/A"}}, "fin": {"TTM": {"Duration": "TTM", "Total Revenue": "240,569", "Cost of Revenue": "112,443", "Gross Profit": "128,126", "Operating Expense": "106,440", "Operating Income": "21,686", "Net Non Operating Interest Income Expense": "-10,826", "Other Income Expense": "-9,351", "Pretax Income": "1,509", "Tax Provision": "2,665", "Net Income Common Stockholders": "-1,073", "Diluted NI Available to Com Stockholders": "-1,073", "Basic EPS": "-", "Diluted EPS": "-", "Basic Average Shares": "-", "Diluted Average Shares": "-", "Total Operating Income as Reported": "11,896", "Total Expenses": "218,883", "Net Income from Continuing & Discontinued Operation": "-1,073", "Normalized Income": "5,731", "Interest Income": "174", "Interest Expense": "11,000", "Net Interest Income": "-10,826", "EBIT": "12,509", "EBITDA": "56,073", "Reconciled Cost of Revenue": "109,546", "Reconciled Depreciation": "43,564", "Net Income from Continuing Operation Net Minority Interest": "-1,073", "Total Unusual Items Excluding Goodwill": "-9,790", "Total Unusual Items": "-9,790", "Normalized EBITDA": "65,863", "Tax Rate for Calcs": "0", "Tax Effect of Unusual Items": "-2,986"}, "12/31/2020": {"Duration": "12/31/2020", "Total Revenue": "240,569", "Cost of Revenue": "112,443", "Gross Profit": "128,126", "Operating Expense": "106,440", "Operating Income": "21,686", "Net Non Operating Interest Income Expense": "-10,826", "Other Income Expense": "-9,351", "Pretax Income": "1,509", "Tax Provision": "2,665", "Net Income Common Stockholders": "-1,073", "Diluted NI Available to Com Stockholders": "-1,073", "Basic EPS": "-0.02", "Diluted EPS": "-0.02", "Basic Average Shares": "54,013", "Diluted Average Shares": "54,013", "Total Operating Income as Reported": "11,896", "Total Expenses": "218,883", "Net Income from Continuing & Discontinued Operation": "-1,073", "Normalized Income": "5,731", "Interest Income": "174", "Interest Expense": "11,000", "Net Interest Income": "-10,826", "EBIT": "12,509", "EBITDA": "-", "Reconciled Cost of Revenue": "109,546", "Reconciled Depreciation": "43,564", "Net Income from Continuing Operation Net Minority Interest": "-1,073", "Total Unusual Items Excluding Goodwill": "-9,790", "Total Unusual Items": "-9,790", "Normalized EBITDA": "65,863", "Tax Rate for Calcs": "0", "Tax Effect of Unusual Items": "-2,986"}, "12/31/2019": {"Duration": "12/31/2019", "Total Revenue": "231,694", "Cost of Revenue": "105,615", "Gross Profit": "126,079", "Operating Expense": "103,994", "Operating Income": "22,085", "Net Non Operating Interest Income Expense": "-11,674", "Other Income Expense": "-2,811", "Pretax Income": "7,600", "Tax Provision": "2,765", "Net Income Common Stockholders": "4,928", "Diluted NI Available to Com Stockholders": "4,928", "Basic EPS": "0.09", "Diluted EPS": "0.09", "Basic Average Shares": "53,379", "Diluted Average Shares": "54,277", "Total Operating Income as Reported": "21,929", "Total Expenses": "209,609", "Net Income from Continuing & Discontinued Operation": "4,928", "Normalized Income": "6,827", "Interest Income": "385", "Interest Expense": "12,059", "Net Interest Income": "-11,674", "EBIT": "19,659", "EBITDA": "-", "Reconciled Cost of Revenue": "105,615", "Reconciled Depreciation": "37,276", "Net Income from Continuing Operation Net Minority Interest": "4,928", "Total Unusual Items Excluding Goodwill": "-2,986", "Total Unusual Items": "-2,986", "Normalized EBITDA": "59,921", "Tax Rate for Calcs": "0", "Tax Effect of Unusual Items": "-1,087"}, "12/31/2018": {"Duration": "12/31/2018", "Total Revenue": "232,468", "Cost of Revenue": "107,509", "Gross Profit": "124,959", "Operating Expense": "100,555", "Operating Income": "24,404", "Net Non Operating Interest Income Expense": "-13,273", "Other Income Expense": "-102", "Pretax Income": "11,029", "Tax Provision": "2,041", "Net Income Common Stockholders": "9,080", "Diluted NI Available to Com Stockholders": "9,080", "Basic EPS": "0.17", "Diluted EPS": "0.17", "Basic Average Shares": "53,042", "Diluted Average Shares": "53,840", "Total Operating Income as Reported": "24,279", "Total Expenses": "208,064", "Net Income from Continuing & Discontinued Operation": "9,080", "Normalized Income": "9,168", "Interest Income": "156", "Interest Expense": "13,429", "Net Interest Income": "-13,273", "EBIT": "24,458", "EBITDA": "-", "Reconciled Cost of Revenue": "107,509", "Reconciled Depreciation": "33,908", "Net Income from Continuing Operation Net Minority Interest": "9,080", "Total Unusual Items Excluding Goodwill": "-125", "Total Unusual Items": "-125", "Normalized EBITDA": "58,491", "Tax Rate for Calcs": "0", "Tax Effect of Unusual Items": "-37.5"}}, "bs": {"12/31/2020": {"Duration": "12/31/2020", "Total Assets": "569,432", "Total Liabilities Net Minority Interest": "403,513", "Total Equity Gross Minority Interest": "165,919", "Total Capitalization": "324,797", "Common Stock Equity": "165,156", "Capital Lease Obligations": "84,495", "Net Tangible Assets": "165,156", "Working Capital": "15,166", "Invested Capital": "333,864", "Tangible Book Value": "165,156", "Total Debt": "253,203", "Net Debt": "149,064", "Share Issued": "54,875", "Ordinary Shares Number": "53,875", "Treasury Shares Number": "1,000"}, "12/31/2019": {"Duration": "12/31/2019", "Total Assets": "557,245", "Total Liabilities Net Minority Interest": "383,736", "Total Equity Gross Minority Interest": "173,509", "Total Capitalization": "340,139", "Common Stock Equity": "172,663", "Capital Lease Obligations": "81,562", "Net Tangible Assets": "172,663", "Working Capital": "26,728", "Invested Capital": "349,045", "Tangible Book Value": "172,663", "Total Debt": "257,944", "Net Debt": "149,720", "Share Issued": "54,085", "Ordinary Shares Number": "53,085", "Treasury Shares Number": "1,000"}, "12/31/2018": {"Duration": "12/31/2018", "Total Assets": "455,185", "Total Liabilities Net Minority Interest": "285,435", "Total Equity Gross Minority Interest": "169,750", "Total Capitalization": "336,834", "Common Stock Equity": "168,811", "Capital Lease Obligations": "170,312", "Net Tangible Assets": "168,811", "Working Capital": "18,227", "Invested Capital": "339,123", "Tangible Book Value": "168,811", "Total Debt": "170,312", "Net Debt": "156,961", "Share Issued": "53,268", "Ordinary Shares Number": "53,268", "Treasury Shares Number": "-"}}, "cf": {"TTM": {"Duration": "TTM", "Operating Cash Flow": "57,119", "Investing Cash Flow": "-50,186", "Financing Cash Flow": "-13,956", "End Cash Position": "20,970", "Income Tax Paid Supplemental Data": "-", "Interest Paid Supplemental Data": "11,137", "Capital Expenditure": "-48,822", "Issuance of Capital Stock": "244", "Issuance of Debt": "0", "Repayment of Debt": "-8,908", "Repurchase of Capital Stock": "0", "Free Cash Flow": "8,297"}, "12/31/2020": {"Duration": "12/31/2020", "Operating Cash Flow": "57,119", "Investing Cash Flow": "-50,186", "Financing Cash Flow": "-13,956", "End Cash Position": "20,970", "Income Tax Paid Supplemental Data": "-", "Interest Paid Supplemental Data": "11,137", "Capital Expenditure": "-48,822", "Issuance of Capital Stock": "244", "Issuance of Debt": "0", "Repayment of Debt": "-8,908", "Repurchase of Capital Stock": "0", "Free Cash Flow": "8,297"}, "12/31/2019": {"Duration": "12/31/2019", "Operating Cash Flow": "58,815", "Investing Cash Flow": "-45,478", "Financing Cash Flow": "-29", "End Cash Position": "28,293", "Income Tax Paid Supplemental Data": "-", "Interest Paid Supplemental Data": "12,228", "Capital Expenditure": "-44,124", "Issuance of Capital Stock": "211", "Issuance of Debt": "180,000", "Repayment of Debt": "-175,292", "Repurchase of Capital Stock": "-1,812", "Free Cash Flow": "14,691"}, "12/31/2018": {"Duration": "12/31/2018", "Operating Cash Flow": "56,195", "Investing Cash Flow": "-40,184", "Financing Cash Flow": "-17,194", "End Cash Position": "14,985", "Income Tax Paid Supplemental Data": "3", "Interest Paid Supplemental Data": "14,254", "Capital Expenditure": "-38,184", "Issuance of Capital Stock": "211", "Issuance of Debt": "14,000", "Repayment of Debt": "-31,030", "Repurchase of Capital Stock": "-", "Free Cash Flow": "18,011"}}}}, {"ATNI": {"quote": {"03/19/2021": {"value": "50.53", "Market Cap": "803.351M", "Beta (5Y Monthly)": "0.29", "PE Ratio (TTM)": "N/A", "EPS (TTM)": "-0.89", "Earnings Date": "Apr 27, 2021 - May 03, 2021", "Forward Dividend & Yield": "0.68 (1.38%)", "Ex-Dividend Date": "Mar 30, 2021", "1y Target Est": "67.33"}}, "fin": {"TTM": {"Duration": "TTM", "Total Revenue": "447,705", "Cost of Revenue": "195,729", "Gross Profit": "259,715", "Operating Expense": "418,588", "Operating Income": "29,117", "Net Non Operating Interest Income Expense": "-4,069", "Other Income Expense": "-13,085", "Pretax Income": "11,963", "Tax Provision": "2,017", "Net Income Common Stockholders": "-4,638", "Diluted NI Available to Com Stockholders": "-4,638", "Basic EPS": "-", "Diluted EPS": "-", "Basic Average Shares": "-", "Diluted Average Shares": "-", "Total Operating Income as Reported": "22,832", "Total Expenses": "418,588", "Net Income from Continuing & Discontinued Operation": "-4,638", "Normalized Income": "587.3289", "Interest Income": "1,127", "Interest Expense": "5,196", "Net Interest Income": "-4,069", "EBIT": "17,159", "EBITDA": "108,526", "Reconciled Cost of Revenue": "195,729", "Reconciled Depreciation": "91,367", "Net Income from Continuing Operation Net Minority Interest": "-4,638", "Total Unusual Items Excluding Goodwill": "-6,285", "Total Unusual Items": "-6,285", "Normalized EBITDA": "114,811", "Tax Rate for Calcs": "0", "Tax Effect of Unusual Items": "-1,060"}, "12/31/2020": {"Duration": "12/31/2020", "Total Revenue": "455,444", "Cost of Revenue": "195,729", "Gross Profit": "259,715", "Operating Expense": "227,322", "Operating Income": "32,393", "Net Non Operating Interest Income Expense": "-4,926", "Other Income Expense": "-27,374", "Pretax Income": "93", "Tax Provision": "801", "Net Income Common Stockholders": "-14,122", "Diluted NI Available to Com Stockholders": "-14,122", "Basic EPS": "-", "Diluted EPS": "-", "Basic Average Shares": "-", "Diluted Average Shares": "-", "Total Operating Income as Reported": "9,180", "Total Expenses": "423,051", "Net Income from Continuing & Discontinued Operation": "-14,122", "Normalized Income": "2,823", "Interest Income": "421", "Interest Expense": "5,347", "Net Interest Income": "-4,926", "EBIT": "5,440", "EBITDA": "-", "Reconciled Cost of Revenue": "195,729", "Reconciled Depreciation": "88,311", "Net Income from Continuing Operation Net Minority Interest": "-14,122", "Total Unusual Items Excluding Goodwill": "-23,213", "Total Unusual Items": "-23,213", "Normalized EBITDA": "116,964", "Tax Rate for Calcs": "0", "Tax Effect of Unusual Items": "-6,268"}, "12/31/2019": {"Duration": "12/31/2019", "Total Revenue": "438,722", "Cost of Revenue": "190,592", "Gross Profit": "248,130", "Operating Expense": "228,389", "Operating Income": "19,741", "Net Non Operating Interest Income Expense": "-2,747", "Other Income Expense": "-10,922", "Pretax Income": "6,072", "Tax Provision": "4,105", "Net Income Common Stockholders": "-10,806", "Diluted NI Available to Com Stockholders": "-10,806", "Basic EPS": "-0.68", "Diluted EPS": "-0.68", "Basic Average Shares": "15,983", "Diluted Average Shares": "15,983", "Total Operating Income as Reported": "13,377", "Total Expenses": "418,981", "Net Income from Continuing & Discontinued Operation": "-10,806", "Normalized Income": "-6,160", "Interest Income": "2,263", "Interest Expense": "5,010", "Net Interest Income": "-2,747", "EBIT": "11,082", "EBITDA": "-", "Reconciled Cost of Revenue": "190,592", "Reconciled Depreciation": "89,125", "Net Income from Continuing Operation Net Minority Interest": "-10,806", "Total Unusual Items Excluding Goodwill": "-6,364", "Total Unusual Items": "-6,364", "Normalized EBITDA": "106,571", "Tax Rate for Calcs": "0", "Tax Effect of Unusual Items": "-1,718"}, "12/31/2018": {"Duration": "12/31/2018", "Total Revenue": "451,207", "Cost of Revenue": "187,509", "Gross Profit": "263,698", "Operating Expense": "225,193", "Operating Income": "38,505", "Net Non Operating Interest Income Expense": "-6,162", "Other Income Expense": "21,399", "Pretax Income": "53,742", "Tax Provision": "18,870", "Net Income Common Stockholders": "19,815", "Diluted NI Available to Com Stockholders": "19,815", "Basic EPS": "1.24", "Diluted EPS": "1.24", "Basic Average Shares": "15,988", "Diluted Average Shares": "16,042", "Total Operating Income as Reported": "61,023", "Total Expenses": "412,702", "Net Income from Continuing & Discontinued Operation": "19,815", "Normalized Income": "5,201", "Interest Income": "1,811", "Interest Expense": "7,973", "Net Interest Income": "-6,162", "EBIT": "61,715", "EBITDA": "-", "Reconciled Cost of Revenue": "187,509", "Reconciled Depreciation": "85,719", "Net Income from Continuing Operation Net Minority Interest": "19,815", "Total Unusual Items Excluding Goodwill": "22,518", "Total Unusual Items": "22,518", "Normalized EBITDA": "124,916", "Tax Rate for Calcs": "0", "Tax Effect of Unusual Items": "7,904"}}, "bs": {"12/31/2020": {"Duration": "12/31/2020", "Total Assets": "1,083,711", "Total Liabilities Net Minority Interest": "329,375", "Total Equity Gross Minority Interest": "754,336", "Total Capitalization": "714,722", "Common Stock Equity": "645,649", "Capital Lease Obligations": "63,453", "Net Tangible Assets": "464,962", "Working Capital": "92,137", "Invested Capital": "718,472", "Tangible Book Value": "464,962", "Total Debt": "136,276", "Share Issued": "17,384", "Ordinary Shares Number": "15,898", "Treasury Shares Number": "1,485"}, "12/31/2019": {"Duration": "12/31/2019", "Total Assets": "1,130,726", "Total Liabilities Net Minority Interest": "324,643", "Total Equity Gross Minority Interest": "806,083", "Total Capitalization": "758,798", "Common Stock Equity": "676,122", "Capital Lease Obligations": "67,570", "Net Tangible Assets": "514,304", "Working Capital": "109,054", "Invested Capital": "762,548", "Tangible Book Value": "514,304", "Total Debt": "153,996", "Share Issued": "17,325", "Ordinary Shares Number": "16,002", "Treasury Shares Number": "1,323"}, "12/31/2018": {"Duration": "12/31/2018", "Total Assets": "1,107,304", "Total Liabilities Net Minority Interest": "283,980", "Total Equity Gross Minority Interest": "823,324", "Total Capitalization": "781,681", "Common Stock Equity": "695,387", "Capital Lease Obligations": "-", "Net Tangible Assets": "528,408", "Working Capital": "135,115", "Invested Capital": "786,369", "Tangible Book Value": "528,408", "Total Debt": "90,982", "Share Issued": "17,274", "Ordinary Shares Number": "16,003", "Treasury Shares Number": "1,272"}}, "cf": {"TTM": {"Duration": "TTM", "Operating Cash Flow": "109,756", "Investing Cash Flow": "-92,712", "Financing Cash Flow": "-37,425", "End Cash Position": "126,301", "Income Tax Paid Supplemental Data": "6,117", "Interest Paid Supplemental Data": "4,829", "Capital Expenditure": "-89,294", "Issuance of Debt": "-", "Repayment of Debt": "-4,689", "Repurchase of Capital Stock": "-2,766", "Free Cash Flow": "20,462"}, "12/31/2020": {"Duration": "12/31/2020", "Operating Cash Flow": "86,284", "Investing Cash Flow": "-70,198", "Financing Cash Flow": "-73,367", "End Cash Position": "104,997", "Income Tax Paid Supplemental Data": "6,117", "Interest Paid Supplemental Data": "4,829", "Capital Expenditure": "-75,323", "Issuance of Debt": "-", "Repayment of Debt": "-13,751", "Repurchase of Capital Stock": "-6,589", "Free Cash Flow": "10,961"}, "12/31/2019": {"Duration": "12/31/2019", "Operating Cash Flow": "87,903", "Investing Cash Flow": "-88,262", "Financing Cash Flow": "-29,908", "End Cash Position": "162,358", "Income Tax Paid Supplemental Data": "30,411", "Interest Paid Supplemental Data": "4,554", "Capital Expenditure": "-72,725", "Issuance of Debt": "0", "Repayment of Debt": "-4,700", "Repurchase of Capital Stock": "-162", "Free Cash Flow": "15,178"}, "12/31/2018": {"Duration": "12/31/2018", "Operating Cash Flow": "115,865", "Investing Cash Flow": "-87,319", "Financing Cash Flow": "-55,230", "End Cash Position": "192,907", "Income Tax Paid Supplemental Data": "12,486", "Interest Paid Supplemental Data": "7,235", "Capital Expenditure": "-185,921", "Issuance of Debt": "0", "Repayment of Debt": "-9,795", "Repurchase of Capital Stock": "-6,198", "Free Cash Flow": "-70,056"}}}}, {"BCE": {"quote": {"03/19/2021": {"value": "45.36", "Market Cap": "41.482B", "Beta (5Y Monthly)": "0.30", "PE Ratio (TTM)": "19.77", "EPS (TTM)": "2.29", "Earnings Date": "N/A", "Forward Dividend & Yield": "2.80 (6.18%)", "Ex-Dividend Date": "Mar 12, 2021", "1y Target Est": "47.54"}}, "fin": {"TTM": {"Duration": "TTM", "Total Revenue": "23,964,000", "Cost of Revenue": "11,903,000", "Gross Profit": "12,061,000", "Operating Expense": "6,215,000", "Operating Income": "5,846,000", "Net Non Operating Interest Income Expense": "-1,195,000", "Other Income Expense": "-265,000", "Pretax Income": "4,386,000", "Tax Provision": "1,133,000", "Net Income Common Stockholders": "3,040,000", "Diluted NI Available to Com Stockholders": "3,040,000", "Basic EPS": "-", "Diluted EPS": "-", "Basic Average Shares": "-", "Diluted Average Shares": "-", "Total Expenses": "18,118,000", "Net Income from Continuing & Discontinued Operation": "3,191,000", "Normalized Income": "3,361,660", "Interest Expense": "1,195,000", "Net Interest Income": "-1,195,000", "EBIT": "5,581,000", "EBITDA": "9,979,000", "Reconciled Cost of Revenue": "11,903,000", "Reconciled Depreciation": "4,398,000", "Net Income from Continuing Operation Net Minority Interest": "3,191,000", "Total Unusual Items Excluding Goodwill": "-230,000", "Total Unusual Items": "-230,000", "Normalized EBITDA": "10,209,000", "Tax Rate for Calcs": "0", "Tax Effect of Unusual Items": "-59,340"}, "12/31/2020": {"Duration": "12/31/2020", "Total Revenue": "22,883,000", "Cost of Revenue": "11,312,000", "Gross Profit": "11,571,000", "Operating Expense": "6,368,000", "Operating Income": "5,203,000", "Net Non Operating Interest Income Expense": "-1,156,000", "Other Income Expense": "-782,000", "Pretax Income": "3,265,000", "Tax Provision": "792,000", "Net Income Common Stockholders": "2,498,000", "Diluted NI Available to Com Stockholders": "2,498,000", "Basic EPS": "-", "Diluted EPS": "-", "Basic Average Shares": "-", "Diluted Average Shares": "-", "Total Expenses": "17,680,000", "Net Income from Continuing & Discontinued Operation": "2,634,000", "Normalized Income": "2,990,133", "Interest Expense": "1,156,000", "Net Interest Income": "-1,156,000", "EBIT": "4,421,000", "EBITDA": "-", "Reconciled Cost of Revenue": "11,312,000", "Reconciled Depreciation": "4,404,000", "Net Income from Continuing Operation Net Minority Interest": "2,408,000", "Total Unusual Items Excluding Goodwill": "-769,000", "Total Unusual Items": "-769,000", "Normalized EBITDA": "9,594,000", "Tax Rate for Calcs": "0", "Tax Effect of Unusual Items": "-186,867"}, "12/31/2019": {"Duration": "12/31/2019", "Total Revenue": "23,964,000", "Cost of Revenue": "11,903,000", "Gross Profit": "12,061,000", "Operating Expense": "6,215,000", "Operating Income": "5,846,000", "Net Non Operating Interest Income Expense": "-1,195,000", "Other Income Expense": "-265,000", "Pretax Income": "4,386,000", "Tax Provision": "1,133,000", "Net Income Common Stockholders": "3,040,000", "Diluted NI Available to Com Stockholders": "3,040,000", "Basic EPS": "3.37", "Diluted EPS": "3.37", "Basic Average Shares": "900,800", "Diluted Average Shares": "901,400", "Total Expenses": "18,118,000", "Net Income from Continuing & Discontinued Operation": "3,191,000", "Normalized Income": "3,361,660", "Interest Expense": "1,195,000", "Net Interest Income": "-1,195,000", "EBIT": "5,581,000", "EBITDA": "-", "Reconciled Cost of Revenue": "11,903,000", "Reconciled Depreciation": "4,398,000", "Net Income from Continuing Operation Net Minority Interest": "3,191,000", "Total Unusual Items Excluding Goodwill": "-230,000", "Total Unusual Items": "-230,000", "Normalized EBITDA": "10,209,000", "Tax Rate for Calcs": "0", "Tax Effect of Unusual Items": "-59,340"}, "12/31/2018": {"Duration": "12/31/2018", "Total Revenue": "23,468,000", "Cost of Revenue": "11,850,000", "Gross Profit": "11,618,000", "Operating Expense": "6,177,000", "Operating Income": "5,441,000", "Net Non Operating Interest Income Expense": "-1,069,000", "Other Income Expense": "-404,000", "Pretax Income": "3,968,000", "Tax Provision": "995,000", "Net Income Common Stockholders": "2,785,000", "Diluted NI Available to Com Stockholders": "2,785,000", "Basic EPS": "3.10", "Diluted EPS": "3.10", "Basic Average Shares": "898,600", "Diluted Average Shares": "898,900", "Total Expenses": "18,027,000", "Net Income from Continuing & Discontinued Operation": "2,929,000", "Normalized Income": "3,212,871", "Interest Expense": "1,069,000", "Net Interest Income": "-1,069,000", "EBIT": "5,037,000", "EBITDA": "-", "Reconciled Cost of Revenue": "11,850,000", "Reconciled Depreciation": "4,014,000", "Net Income from Continuing Operation Net Minority Interest": "2,929,000", "Total Unusual Items Excluding Goodwill": "-379,000", "Total Unusual Items": "-379,000", "Normalized EBITDA": "9,430,000", "Tax Rate for Calcs": "0", "Tax Effect of Unusual Items": "-95,129"}}, "bs": {"12/31/2020": {"Duration": "12/31/2020", "Total Assets": "60,665,000", "Total Liabilities Net Minority Interest": "39,336,000", "Total Equity Gross Minority Interest": "21,329,000", "Total Capitalization": "44,895,000", "Preferred Stock Equity": "4,003,000", "Common Stock Equity": "16,986,000", "Net Tangible Assets": "-2,717,000", "Working Capital": "-2,583,000", "Invested Capital": "43,309,000", "Tangible Book Value": "-6,720,000", "Total Debt": "26,323,000", "Net Debt": "26,099,000", "Share Issued": "904,415", "Ordinary Shares Number": "904,415", "Preferred Shares Number": "160,259"}, "12/31/2019": {"Duration": "12/31/2019", "Total Assets": "60,146,000", "Total Liabilities Net Minority Interest": "38,738,000", "Total Equity Gross Minority Interest": "21,408,000", "Total Capitalization": "43,489,000", "Preferred Stock Equity": "4,004,000", "Common Stock Equity": "17,070,000", "Net Tangible Assets": "-2,945,000", "Working Capital": "-4,257,000", "Invested Capital": "43,366,000", "Tangible Book Value": "-6,949,000", "Total Debt": "26,296,000", "Net Debt": "26,151,000", "Share Issued": "903,908", "Ordinary Shares Number": "903,908", "Preferred Shares Number": "160,300"}, "12/31/2018": {"Duration": "12/31/2018", "Total Assets": "57,100,000", "Total Liabilities Net Minority Interest": "36,411,000", "Total Equity Gross Minority Interest": "20,689,000", "Total Capitalization": "40,123,000", "Preferred Stock Equity": "4,004,000", "Common Stock Equity": "16,359,000", "Net Tangible Assets": "-3,500,000", "Working Capital": "-4,636,000", "Invested Capital": "40,764,000", "Tangible Book Value": "-7,504,000", "Total Debt": "24,405,000", "Net Debt": "23,980,000", "Share Issued": "898,200", "Ordinary Shares Number": "898,200", "Preferred Shares Number": "160,300"}}, "cf": {"TTM": {"Duration": "TTM", "Operating Cash Flow": "7,958,000", "Investing Cash Flow": "-4,036,000", "Financing Cash Flow": "-4,202,000", "End Cash Position": "145,000", "Capital Expenditure": "-3,988,000", "Issuance of Capital Stock": "240,000", "Issuance of Debt": "2,085,000", "Repayment of Debt": "-3,301,000", "Repurchase of Capital Stock": "0", "Free Cash Flow": "3,970,000"}, "12/31/2020": {"Duration": "12/31/2020", "Operating Cash Flow": "7,754,000", "Investing Cash Flow": "-3,540,000", "Financing Cash Flow": "-4,135,000", "End Cash Position": "224,000", "Capital Expenditure": "-4,288,000", "Issuance of Capital Stock": "26,000", "Issuance of Debt": "6,006,000", "Repayment of Debt": "-6,644,000", "Repurchase of Capital Stock": "-", "Free Cash Flow": "3,466,000"}, "12/31/2019": {"Duration": "12/31/2019", "Operating Cash Flow": "7,958,000", "Investing Cash Flow": "-4,036,000", "Financing Cash Flow": "-4,202,000", "End Cash Position": "145,000", "Capital Expenditure": "-3,988,000", "Issuance of Capital Stock": "240,000", "Issuance of Debt": "1,954,000", "Repayment of Debt": "-3,301,000", "Repurchase of Capital Stock": "0", "Free Cash Flow": "3,970,000"}, "12/31/2018": {"Duration": "12/31/2018", "Operating Cash Flow": "7,384,000", "Investing Cash Flow": "-4,386,000", "Financing Cash Flow": "-3,198,000", "End Cash Position": "425,000", "Capital Expenditure": "-4,027,000", "Issuance of Capital Stock": "11,000", "Issuance of Debt": "2,996,000", "Repayment of Debt": "-2,836,000", "Repurchase of Capital Stock": "-175,000", "Free Cash Flow": "3,357,000"}}}}, {"CBB": {"quote": {"03/19/2021": {"value": "15.41", "Market Cap": "784.502M", "Beta (5Y Monthly)": "0.44", "PE Ratio (TTM)": "N/A", "EPS (TTM)": "-1.30", "Earnings Date": "May 03, 2021 - May 07, 2021", "Forward Dividend & Yield": "N/A (N/A)", "Ex-Dividend Date": "Jul 02, 1999", "1y Target Est": "15.50"}}, "fin": {"TTM": {"Duration": "TTM", "Total Revenue": "1,559,800", "Cost of Revenue": "802,000", "Gross Profit": "757,800", "Operating Expense": "639,900", "Operating Income": "117,900", "Net Non Operating Interest Income Expense": "-134,200", "Other Income Expense": "-64,800", "Pretax Income": "-81,100", "Tax Provision": "-25,500", "Net Income Common Stockholders": "-66,000", "Diluted NI Available to Com Stockholders": "-66,000", "Basic EPS": "-", "Diluted EPS": "-", "Basic Average Shares": "-", "Diluted Average Shares": "-", "Total Operating Income as Reported": "66,000", "Total Expenses": "1,441,900", "Net Income from Continuing & Discontinued Operation": "-55,600", "Normalized Income": "-20,048", "Interest Expense": "134,200", "Net Interest Income": "-134,200", "EBIT": "53,100", "EBITDA": "346,500", "Reconciled Cost of Revenue": "802,000", "Reconciled Depreciation": "293,400", "Net Income from Continuing Operation Net Minority Interest": "-55,600", "Total Unusual Items Excluding Goodwill": "-51,900", "Total Unusual Items": "-51,900", "Normalized EBITDA": "398,400", "Tax Rate for Calcs": "0", "Tax Effect of Unusual Items": "-16,348"}, "12/31/2020": {"Duration": "12/31/2020", "Total Revenue": "1,559,800", "Cost of Revenue": "802,000", "Gross Profit": "757,800", "Operating Expense": "639,900", "Operating Income": "117,900", "Net Non Operating Interest Income Expense": "-134,200", "Other Income Expense": "-64,800", "Pretax Income": "-81,100", "Tax Provision": "-25,500", "Net Income Common Stockholders": "-66,000", "Diluted NI Available to Com Stockholders": "-66,000", "Basic EPS": "-", "Diluted EPS": "-", "Basic Average Shares": "-", "Diluted Average Shares": "-", "Total Operating Income as Reported": "66,000", "Total Expenses": "1,441,900", "Net Income from Continuing & Discontinued Operation": "-55,600", "Normalized Income": "-20,048", "Interest Expense": "134,200", "Net Interest Income": "-134,200", "EBIT": "53,100", "EBITDA": "-", "Reconciled Cost of Revenue": "802,000", "Reconciled Depreciation": "293,400", "Net Income from Continuing Operation Net Minority Interest": "-55,600", "Total Unusual Items Excluding Goodwill": "-51,900", "Total Unusual Items": "-51,900", "Normalized EBITDA": "398,400", "Tax Rate for Calcs": "0", "Tax Effect of Unusual Items": "-16,348"}, "12/31/2019": {"Duration": "12/31/2019", "Total Revenue": "1,536,700", "Cost of Revenue": "784,600", "Gross Profit": "752,100", "Operating Expense": "659,300", "Operating Income": "92,800", "Net Non Operating Interest Income Expense": "-139,600", "Other Income Expense": "-30,400", "Pretax Income": "-77,200", "Tax Provision": "-10,600", "Net Income Common Stockholders": "-77,000", "Diluted NI Available to Com Stockholders": "-77,000", "Basic EPS": "-1.53", "Diluted EPS": "-1.53", "Basic Average Shares": "50,400", "Diluted Average Shares": "50,400", "Total Operating Income as Reported": "73,100", "Total Expenses": "1,443,900", "Net Income from Continuing & Discontinued Operation": "-66,600", "Normalized Income": "-49,599", "Interest Expense": "139,600", "Net Interest Income": "-139,600", "EBIT": "62,400", "EBITDA": "-", "Reconciled Cost of Revenue": "784,600", "Reconciled Depreciation": "304,900", "Net Income from Continuing Operation Net Minority Interest": "-66,600", "Total Unusual Items Excluding Goodwill": "-19,700", "Total Unusual Items": "-19,700", "Normalized EBITDA": "387,000", "Tax Rate for Calcs": "0", "Tax Effect of Unusual Items": "-2,699"}, "12/31/2018": {"Duration": "12/31/2018", "Total Revenue": "1,378,200", "Cost of Revenue": "698,700", "Gross Profit": "679,500", "Operating Expense": "565,400", "Operating Income": "114,100", "Net Non Operating Interest Income Expense": "-131,500", "Other Income Expense": "-43,000", "Pretax Income": "-60,400", "Tax Provision": "9,400", "Net Income Common Stockholders": "-80,200", "Diluted NI Available to Com Stockholders": "-80,200", "Basic EPS": "-1.73", "Diluted EPS": "-1.73", "Basic Average Shares": "46,300", "Diluted Average Shares": "46,300", "Total Operating Income as Reported": "83,300", "Total Expenses": "1,264,100", "Net Income from Continuing & Discontinued Operation": "-69,800", "Normalized Income": "-46,367", "Interest Expense": "131,500", "Net Interest Income": "-131,500", "EBIT": "71,100", "EBITDA": "-", "Reconciled Cost of Revenue": "698,700", "Reconciled Depreciation": "252,000", "Net Income from Continuing Operation Net Minority Interest": "-69,800", "Total Unusual Items Excluding Goodwill": "-32,100", "Total Unusual Items": "-32,100", "Normalized EBITDA": "355,200", "Tax Rate for Calcs": "0", "Tax Effect of Unusual Items": "-8,667"}}, "bs": {"12/31/2020": {"Duration": "12/31/2020", "Total Assets": "2,668,600", "Total Liabilities Net Minority Interest": "2,859,700", "Total Equity Gross Minority Interest": "-191,100", "Total Capitalization": "1,706,700", "Preferred Stock Equity": "129,400", "Common Stock Equity": "-320,500", "Capital Lease Obligations": "99,600", "Net Tangible Assets": "-500,700", "Working Capital": "-87,000", "Invested Capital": "1,585,200", "Tangible Book Value": "-630,100", "Total Debt": "2,005,300", "Net Debt": "1,893,500", "Share Issued": "50,681", "Ordinary Shares Number": "50,681", "Preferred Shares Number": "3,105"}, "12/31/2019": {"Duration": "12/31/2019", "Total Assets": "2,653,800", "Total Liabilities Net Minority Interest": "2,793,800", "Total Equity Gross Minority Interest": "-140,000", "Total Capitalization": "1,701,800", "Preferred Stock Equity": "129,400", "Common Stock Equity": "-269,400", "Capital Lease Obligations": "105,900", "Net Tangible Assets": "-455,900", "Working Capital": "-119,700", "Invested Capital": "1,580,400", "Tangible Book Value": "-585,300", "Total Debt": "1,955,700", "Net Debt": "1,838,200", "Share Issued": "50,421", "Ordinary Shares Number": "50,421", "Preferred Shares Number": "3,105"}, "12/31/2018": {"Duration": "12/31/2018", "Total Assets": "2,730,200", "Total Liabilities Net Minority Interest": "2,805,200", "Total Equity Gross Minority Interest": "-75,000", "Total Capitalization": "1,774,100", "Preferred Stock Equity": "129,400", "Common Stock Equity": "-204,400", "Capital Lease Obligations": "61,300", "Net Tangible Assets": "-400,100", "Working Capital": "-95,800", "Invested Capital": "1,664,100", "Tangible Book Value": "-529,500", "Total Debt": "1,929,800", "Net Debt": "1,853,100", "Share Issued": "50,184", "Ordinary Shares Number": "50,184", "Preferred Shares Number": "3,105"}}, "cf": {"TTM": {"Duration": "TTM", "Operating Cash Flow": "206,100", "Investing Cash Flow": "-226,400", "Financing Cash Flow": "25,600", "End Cash Position": "17,200", "Interest Paid Supplemental Data": "-", "Capital Expenditure": "-230,000", "Issuance of Debt": "-", "Repayment of Debt": "-22,400", "Repurchase of Capital Stock": "-", "Free Cash Flow": "-23,900"}, "12/31/2020": {"Duration": "12/31/2020", "Operating Cash Flow": "206,100", "Investing Cash Flow": "-226,400", "Financing Cash Flow": "25,600", "End Cash Position": "17,200", "Interest Paid Supplemental Data": "-", "Capital Expenditure": "-230,000", "Issuance of Debt": "-", "Repayment of Debt": "-22,400", "Repurchase of Capital Stock": "-", "Free Cash Flow": "-23,900"}, "12/31/2019": {"Duration": "12/31/2019", "Operating Cash Flow": "259,100", "Investing Cash Flow": "-223,300", "Financing Cash Flow": "-39,600", "End Cash Position": "11,600", "Interest Paid Supplemental Data": "-", "Capital Expenditure": "-223,800", "Issuance of Debt": "0", "Repayment of Debt": "-21,500", "Repurchase of Capital Stock": "-", "Free Cash Flow": "35,300"}, "12/31/2018": {"Duration": "12/31/2018", "Operating Cash Flow": "214,700", "Investing Cash Flow": "-437,400", "Financing Cash Flow": "-158,100", "End Cash Position": "15,400", "Interest Paid Supplemental Data": "131,700", "Capital Expenditure": "-220,600", "Issuance of Debt": "0", "Repayment of Debt": "-328,700", "Repurchase of Capital Stock": "0", "Free Cash Flow": "-5,900"}}}}, {"VZ": {"quote": {"03/19/2021": {"value": "56.24", "Market Cap": "232.73B", "Beta (5Y Monthly)": "0.47", "PE Ratio (TTM)": "13.08", "EPS (TTM)": "4.30", "Earnings Date": "Apr 21, 2021", "Forward Dividend & Yield": "2.51 (4.46%)", "Ex-Dividend Date": "Apr 08, 2021", "1y Target Est": "59.88"}}, "fin": {"TTM": {"Duration": "TTM", "Total Revenue": "128,292,000", "Cost of Revenue": "51,201,000", "Gross Profit": "77,091,000", "Operating Expense": "48,293,000", "Operating Income": "28,798,000", "Net Non Operating Interest Income Expense": "-4,182,000", "Other Income Expense": "-649,000", "Pretax Income": "23,967,000", "Tax Provision": "5,619,000", "Net Income Common Stockholders": "17,801,000", "Diluted NI Available to Com Stockholders": "17,801,000", "Basic EPS": "-", "Diluted EPS": "-", "Basic Average Shares": "-", "Diluted Average Shares": "-", "Total Operating Income as Reported": "28,798,000", "Total Expenses": "99,494,000", "Net Income from Continuing & Discontinued Operation": "17,801,000", "Normalized Income": "17,899,814", "Interest Income": "65,000", "Interest Expense": "4,247,000", "Net Interest Income": "-4,182,000", "EBIT": "28,214,000", "EBITDA": "44,934,000", "Reconciled Cost of Revenue": "51,201,000", "Reconciled Depreciation": "16,720,000", "Net Income from Continuing Operation Net Minority Interest": "17,801,000", "Total Unusual Items Excluding Goodwill": "-129,000", "Total Unusual Items": "-129,000", "Normalized EBITDA": "45,063,000", "Tax Rate for Calcs": "0", "Tax Effect of Unusual Items": "-30,186"}, "12/31/2020": {"Duration": "12/31/2020", "Total Revenue": "128,292,000", "Cost of Revenue": "51,201,000", "Gross Profit": "77,091,000", "Operating Expense": "48,293,000", "Operating Income": "28,798,000", "Net Non Operating Interest Income Expense": "-4,182,000", "Other Income Expense": "-649,000", "Pretax Income": "23,967,000", "Tax Provision": "5,619,000", "Net Income Common Stockholders": "17,801,000", "Diluted NI Available to Com Stockholders": "17,801,000", "Basic EPS": "-", "Diluted EPS": "-", "Basic Average Shares": "-", "Diluted Average Shares": "-", "Total Operating Income as Reported": "28,798,000", "Total Expenses": "99,494,000", "Net Income from Continuing & Discontinued Operation": "17,801,000", "Normalized Income": "17,899,814", "Interest Income": "65,000", "Interest Expense": "4,247,000", "Net Interest Income": "-4,182,000", "EBIT": "28,214,000", "EBITDA": "-", "Reconciled Cost of Revenue": "51,201,000", "Reconciled Depreciation": "16,720,000", "Net Income from Continuing Operation Net Minority Interest": "17,801,000", "Total Unusual Items Excluding Goodwill": "-129,000", "Total Unusual Items": "-129,000", "Normalized EBITDA": "45,063,000", "Tax Rate for Calcs": "0", "Tax Effect of Unusual Items": "-30,186"}, "12/31/2019": {"Duration": "12/31/2019", "Total Revenue": "131,868,000", "Cost of Revenue": "54,726,000", "Gross Profit": "77,142,000", "Operating Expense": "46,672,000", "Operating Income": "30,470,000", "Net Non Operating Interest Income Expense": "-4,609,000", "Other Income Expense": "-3,128,000", "Pretax Income": "22,733,000", "Tax Provision": "2,945,000", "Net Income Common Stockholders": "19,265,000", "Diluted NI Available to Com Stockholders": "19,265,000", "Basic EPS": "4.66", "Diluted EPS": "4.65", "Basic Average Shares": "4,138,000", "Diluted Average Shares": "4,140,000", "Total Operating Income as Reported": "30,378,000", "Total Expenses": "101,398,000", "Net Income from Continuing & Discontinued Operation": "19,265,000", "Normalized Income": "22,482,193", "Interest Income": "121,000", "Interest Expense": "4,730,000", "Net Interest Income": "-4,609,000", "EBIT": "27,463,000", "EBITDA": "-", "Reconciled Cost of Revenue": "54,726,000", "Reconciled Depreciation": "16,682,000", "Net Income from Continuing Operation Net Minority Interest": "19,265,000", "Total Unusual Items Excluding Goodwill": "-3,696,000", "Total Unusual Items": "-3,696,000", "Normalized EBITDA": "47,841,000", "Tax Rate for Calcs": "0", "Tax Effect of Unusual Items": "-478,807"}, "12/31/2018": {"Duration": "12/31/2018", "Total Revenue": "130,863,000", "Cost of Revenue": "55,508,000", "Gross Profit": "75,355,000", "Operating Expense": "48,486,000", "Operating Income": "26,869,000", "Net Non Operating Interest Income Expense": "-4,739,000", "Other Income Expense": "-2,507,000", "Pretax Income": "19,623,000", "Tax Provision": "3,584,000", "Net Income Common Stockholders": "15,528,000", "Diluted NI Available to Com Stockholders": "15,528,000", "Basic EPS": "3.76", "Diluted EPS": "3.76", "Basic Average Shares": "4,128,000", "Diluted Average Shares": "4,132,000", "Total Operating Income as Reported": "22,278,000", "Total Expenses": "103,994,000", "Net Income from Continuing & Discontinued Operation": "15,528,000", "Normalized Income": "19,280,487", "Interest Income": "94,000", "Interest Expense": "4,833,000", "Net Interest Income": "-4,739,000", "EBIT": "24,456,000", "EBITDA": "-", "Reconciled Cost of Revenue": "55,508,000", "Reconciled Depreciation": "17,403,000", "Net Income from Continuing Operation Net Minority Interest": "15,528,000", "Total Unusual Items Excluding Goodwill": "-4,591,000", "Total Unusual Items": "-4,591,000", "Normalized EBITDA": "46,450,000", "Tax Rate for Calcs": "0", "Tax Effect of Unusual Items": "-838,513"}}, "bs": {"12/31/2020": {"Duration": "12/31/2020", "Total Assets": "316,481,000", "Total Liabilities Net Minority Interest": "247,209,000", "Total Equity Gross Minority Interest": "69,272,000", "Total Capitalization": "191,015,000", "Common Stock Equity": "67,842,000", "Capital Lease Obligations": "21,485,000", "Net Tangible Assets": "-62,441,000", "Working Capital": "14,934,000", "Invested Capital": "196,904,000", "Tangible Book Value": "-62,441,000", "Total Debt": "150,547,000", "Net Debt": "106,891,000", "Share Issued": "4,291,434", "Ordinary Shares Number": "4,138,130", "Treasury Shares Number": "153,304"}, "12/31/2019": {"Duration": "12/31/2019", "Total Assets": "291,727,000", "Total Liabilities Net Minority Interest": "228,892,000", "Total Equity Gross Minority Interest": "62,835,000", "Total Capitalization": "161,327,000", "Common Stock Equity": "61,395,000", "Capital Lease Obligations": "22,770,000", "Net Tangible Assets": "-67,551,000", "Working Capital": "-7,395,000", "Invested Capital": "171,768,000", "Tangible Book Value": "-67,551,000", "Total Debt": "133,143,000", "Net Debt": "107,779,000", "Share Issued": "4,291,434", "Ordinary Shares Number": "4,135,828", "Treasury Shares Number": "155,606"}, "12/31/2018": {"Duration": "12/31/2018", "Total Assets": "264,829,000", "Total Liabilities Net Minority Interest": "210,119,000", "Total Equity Gross Minority Interest": "54,710,000", "Total Capitalization": "159,018,000", "Common Stock Equity": "53,145,000", "Capital Lease Obligations": "-", "Net Tangible Assets": "-75,374,000", "Working Capital": "-3,294,000", "Invested Capital": "166,208,000", "Tangible Book Value": "-75,374,000", "Total Debt": "113,063,000", "Net Debt": "110,318,000", "Share Issued": "4,291,434", "Ordinary Shares Number": "4,132,033", "Treasury Shares Number": "159,400"}}, "cf": {"TTM": {"Duration": "TTM", "Operating Cash Flow": "41,768,000", "Investing Cash Flow": "-23,512,000", "Financing Cash Flow": "1,325,000", "End Cash Position": "23,498,000", "Capital Expenditure": "-20,318,000", "Issuance of Debt": "31,457,000", "Repayment of Debt": "-17,188,000", "Repurchase of Capital Stock": "-", "Free Cash Flow": "21,450,000"}, "12/31/2020": {"Duration": "12/31/2020", "Operating Cash Flow": "41,768,000", "Investing Cash Flow": "-23,512,000", "Financing Cash Flow": "1,325,000", "End Cash Position": "23,498,000", "Capital Expenditure": "-20,318,000", "Issuance of Debt": "31,457,000", "Repayment of Debt": "-17,188,000", "Repurchase of Capital Stock": "-", "Free Cash Flow": "21,450,000"}, "12/31/2019": {"Duration": "12/31/2019", "Operating Cash Flow": "35,746,000", "Investing Cash Flow": "-17,581,000", "Financing Cash Flow": "-18,164,000", "End Cash Position": "3,917,000", "Capital Expenditure": "-18,837,000", "Issuance of Debt": "18,655,000", "Repayment of Debt": "-23,886,000", "Repurchase of Capital Stock": "-", "Free Cash Flow": "16,909,000"}, "12/31/2018": {"Duration": "12/31/2018", "Operating Cash Flow": "34,339,000", "Investing Cash Flow": "-17,934,000", "Financing Cash Flow": "-15,377,000", "End Cash Position": "3,916,000", "Capital Expenditure": "-18,087,000", "Issuance of Debt": "10,777,000", "Repayment of Debt": "-14,558,000", "Repurchase of Capital Stock": "-", "Free Cash Flow": "16,252,000"}}}}, {"CNSL": {"quote": {"03/19/2021": {"value": "6.80", "Market Cap": "538.649M", "Beta (5Y Monthly)": "1.35", "PE Ratio (TTM)": "14.50", "EPS (TTM)": "0.47", "Earnings Date": "Apr 28, 2021 - May 03, 2021", "Forward Dividend & Yield": "N/A (N/A)", "Ex-Dividend Date": "Apr 12, 2019", "1y Target Est": "6.50"}}, "fin": {"TTM": {"Duration": "TTM", "Total Revenue": "1,315,199", "Cost of Revenue": "560,126", "Gross Profit": "755,073", "Operating Expense": "627,680", "Operating Income": "127,393", "Net Non Operating Interest Income Expense": "-131,194", "Other Income Expense": "40,451", "Pretax Income": "36,650", "Tax Provision": "12,525", "Net Income Common Stockholders": "23,044", "Diluted NI Available to Com Stockholders": "23,044", "Basic EPS": "-", "Diluted EPS": "-", "Basic Average Shares": "-", "Diluted Average Shares": "-", "Total Operating Income as Reported": "127,393", "Total Expenses": "1,187,806", "Net Income from Continuing & Discontinued Operation": "23,656", "Normalized Income": "-4,643", "Interest Expense": "143,591", "Net Interest Income": "-131,194", "EBIT": "127,393", "EBITDA": "475,887", "Reconciled Cost of Revenue": "560,126", "Reconciled Depreciation": "348,494", "Net Income from Continuing Operation Net Minority Interest": "23,656", "Total Unusual Items Excluding Goodwill": "42,991", "Total Unusual Items": "42,991", "Normalized EBITDA": "432,896", "Tax Rate for Calcs": "0", "Tax Effect of Unusual Items": "14,692"}, "12/31/2020": {"Duration": "12/31/2020", "Total Revenue": "1,304,028", "Cost of Revenue": "560,644", "Gross Profit": "743,384", "Operating Expense": "600,225", "Operating Income": "143,159", "Net Non Operating Interest Income Expense": "-143,591", "Other Income Expense": "48,670", "Pretax Income": "48,238", "Tax Provision": "10,936", "Net Income Common Stockholders": "34,133", "Diluted NI Available to Com Stockholders": "34,133", "Basic EPS": "-", "Diluted EPS": "-", "Basic Average Shares": "-", "Diluted Average Shares": "-", "Total Operating Income as Reported": "135,513", "Total Expenses": "1,160,869", "Net Income from Continuing & Discontinued Operation": "36,977", "Normalized Income": "25,265", "Interest Expense": "143,591", "Net Interest Income": "-143,591", "EBIT": "191,829", "EBITDA": "-", "Reconciled Cost of Revenue": "560,644", "Reconciled Depreciation": "324,864", "Net Income from Continuing Operation Net Minority Interest": "36,977", "Total Unusual Items Excluding Goodwill": "15,152", "Total Unusual Items": "15,152", "Normalized EBITDA": "501,541", "Tax Rate for Calcs": "0", "Tax Effect of Unusual Items": "3,440"}, "12/31/2019": {"Duration": "12/31/2019", "Total Revenue": "1,336,542", "Cost of Revenue": "574,936", "Gross Profit": "761,606", "Operating Expense": "680,325", "Operating Income": "81,281", "Net Non Operating Interest Income Expense": "-136,660", "Other Income Expense": "31,734", "Pretax Income": "-23,645", "Tax Provision": "-3,714", "Net Income Common Stockholders": "-20,845", "Diluted NI Available to Com Stockholders": "-20,845", "Basic EPS": "-0.29", "Diluted EPS": "-0.29", "Basic Average Shares": "70,837", "Diluted Average Shares": "70,837", "Total Operating Income as Reported": "81,281", "Total Expenses": "1,255,261", "Net Income from Continuing & Discontinued Operation": "-20,383", "Normalized Income": "-56,293", "Interest Expense": "136,660", "Net Interest Income": "-136,660", "EBIT": "113,015", "EBITDA": "-", "Reconciled Cost of Revenue": "574,936", "Reconciled Depreciation": "381,237", "Net Income from Continuing Operation Net Minority Interest": "-20,383", "Total Unusual Items Excluding Goodwill": "42,598", "Total Unusual Items": "42,598", "Normalized EBITDA": "451,654", "Tax Rate for Calcs": "0", "Tax Effect of Unusual Items": "6,688"}, "12/31/2018": {"Duration": "12/31/2018", "Total Revenue": "1,399,074", "Cost of Revenue": "611,872", "Gross Profit": "787,202", "Operating Expense": "766,273", "Operating Income": "20,929", "Net Non Operating Interest Income Expense": "-134,578", "Other Income Expense": "38,951", "Pretax Income": "-74,698", "Tax Provision": "-24,127", "Net Income Common Stockholders": "-51,644", "Diluted NI Available to Com Stockholders": "-51,644", "Basic EPS": "-0.73", "Diluted EPS": "-0.73", "Basic Average Shares": "70,613", "Diluted Average Shares": "70,613", "Total Operating Income as Reported": "18,969", "Total Expenses": "1,378,145", "Net Income from Continuing & Discontinued Operation": "-50,834", "Normalized Income": "-76,314", "Interest Expense": "134,578", "Net Interest Income": "-134,578", "EBIT": "59,880", "EBITDA": "-", "Reconciled Cost of Revenue": "611,872", "Reconciled Depreciation": "432,668", "Net Income from Continuing Operation Net Minority Interest": "-50,834", "Total Unusual Items Excluding Goodwill": "37,636", "Total Unusual Items": "37,636", "Normalized EBITDA": "454,912", "Tax Rate for Calcs": "0", "Tax Effect of Unusual Items": "12,156"}}, "bs": {"12/31/2020": {"Duration": "12/31/2020", "Total Assets": "3,507,300", "Total Liabilities Net Minority Interest": "3,118,072", "Total Equity Gross Minority Interest": "389,228", "Total Capitalization": "2,315,199", "Common Stock Equity": "382,533", "Net Tangible Assets": "-776,716", "Working Capital": "70,191", "Invested Capital": "2,332,760", "Tangible Book Value": "-776,716", "Total Debt": "1,950,227", "Net Debt": "1,794,666", "Share Issued": "79,228", "Ordinary Shares Number": "79,228"}, "12/31/2019": {"Duration": "12/31/2019", "Total Assets": "3,390,277", "Total Liabilities Net Minority Interest": "3,043,026", "Total Equity Gross Minority Interest": "347,251", "Total Capitalization": "2,591,558", "Common Stock Equity": "340,881", "Net Tangible Assets": "-869,019", "Working Capital": "-67,429", "Invested Capital": "2,618,859", "Tangible Book Value": "-869,019", "Total Debt": "2,277,978", "Net Debt": "2,265,583", "Share Issued": "71,961", "Ordinary Shares Number": "71,961"}, "12/31/2018": {"Duration": "12/31/2018", "Total Assets": "3,535,261", "Total Liabilities Net Minority Interest": "3,119,607", "Total Equity Gross Minority Interest": "415,654", "Total Capitalization": "2,713,321", "Common Stock Equity": "409,736", "Net Tangible Assets": "-866,023", "Working Capital": "-85,471", "Invested Capital": "2,743,789", "Tangible Book Value": "-866,023", "Total Debt": "2,334,053", "Net Debt": "2,324,454", "Share Issued": "71,187", "Ordinary Shares Number": "71,187"}}, "cf": {"TTM": {"Duration": "TTM", "Operating Cash Flow": "357,555", "Investing Cash Flow": "-201,871", "Financing Cash Flow": "-120,258", "End Cash Position": "45,876", "Capital Expenditure": "-208,672", "Issuance of Capital Stock": "350,000", "Issuance of Debt": "128,000", "Repayment of Debt": "-247,895", "Repurchase of Capital Stock": "-812", "Free Cash Flow": "148,883"}, "12/31/2020": {"Duration": "12/31/2020", "Operating Cash Flow": "364,980", "Investing Cash Flow": "-210,066", "Financing Cash Flow": "-11,748", "End Cash Position": "155,561", "Capital Expenditure": "-217,563", "Issuance of Capital Stock": "350,000", "Issuance of Debt": "2,021,250", "Repayment of Debt": "-2,321,575", "Repurchase of Capital Stock": "-812", "Free Cash Flow": "147,417"}, "12/31/2019": {"Duration": "12/31/2019", "Operating Cash Flow": "339,096", "Investing Cash Flow": "-217,819", "Financing Cash Flow": "-118,481", "End Cash Position": "12,395", "Capital Expenditure": "-232,203", "Issuance of Capital Stock": "-", "Issuance of Debt": "195,000", "Repayment of Debt": "-257,673", "Repurchase of Capital Stock": "-363", "Free Cash Flow": "106,893"}, "12/31/2018": {"Duration": "12/31/2018", "Operating Cash Flow": "357,321", "Investing Cash Flow": "-221,459", "Financing Cash Flow": "-141,920", "End Cash Position": "9,599", "Capital Expenditure": "-244,816", "Issuance of Capital Stock": "-", "Issuance of Debt": "189,588", "Repayment of Debt": "-220,693", "Repurchase of Capital Stock": "-593", "Free Cash Flow": "112,505"}}}}, {"CALL": {"quote": {"03/19/2021": {"value": "", "Net Assets": "N/A", "Beta (5Y Monthly)": "N/A", "Yield": "N/A", "5y Average Return": "N/A", "Holdings Turnover": "N/A", "Last Dividend": "N/A", "Average for Category": "N/A", "Inception Date": "N/A"}}, "fin": {}, "bs": {}, "cf": {}}}, {"SHEN": {"quote": {"03/19/2021": {"value": "49.01", "Market Cap": "2.447B", "Beta (5Y Monthly)": "0.41", "PE Ratio (TTM)": "19.36", "EPS (TTM)": "2.53", "Earnings Date": "Apr 28, 2021 - May 03, 2021", "Forward Dividend & Yield": "0.34 (0.69%)", "Ex-Dividend Date": "Nov 10, 2020", "1y Target Est": "41.50"}}, "fin": {"TTM": {"Duration": "TTM", "Total Revenue": "220,775", "Cost of Revenue": "88,203", "Gross Profit": "132,572", "Operating Expense": "133,719", "Operating Income": "-1,147", "Net Non Operating Interest Income Expense": "-", "Other Income Expense": "3,187", "Pretax Income": "2,040", "Tax Provision": "-586", "Net Income Common Stockholders": "126,723", "Diluted NI Available to Com Stockholders": "126,723", "Basic EPS": "-", "Diluted EPS": "-", "Basic Average Shares": "-", "Diluted Average Shares": "-", "Total Operating Income as Reported": "-1,147", "Total Expenses": "221,922", "Net Income from Continuing & Discontinued Operation": "126,723", "Normalized Income": "2,626", "Interest Expense": "-", "Net Interest Income": "-", "EBIT": "-1,147", "EBITDA": "47,556", "Reconciled Cost of Revenue": "88,203", "Reconciled Depreciation": "48,703", "Net Income from Continuing Operation Net Minority Interest": "2,626", "Total Unusual Items Excluding Goodwill": "-", "Total Unusual Items": "-", "Normalized EBITDA": "47,556", "Tax Rate for Calcs": "0", "Tax Effect of Unusual Items": "0"}, "12/31/2020": {"Duration": "12/31/2020", "Total Revenue": "220,775", "Cost of Revenue": "88,203", "Gross Profit": "132,572", "Operating Expense": "133,719", "Operating Income": "-1,147", "Net Non Operating Interest Income Expense": "-", "Other Income Expense": "3,187", "Pretax Income": "2,040", "Tax Provision": "-586", "Net Income Common Stockholders": "126,723", "Diluted NI Available to Com Stockholders": "126,723", "Basic EPS": "-", "Diluted EPS": "-", "Basic Average Shares": "-", "Diluted Average Shares": "-", "Total Operating Income as Reported": "-1,147", "Total Expenses": "221,922", "Net Income from Continuing & Discontinued Operation": "126,723", "Normalized Income": "2,626", "Interest Expense": "-", "Net Interest Income": "-", "EBIT": "-1,147", "EBITDA": "-", "Reconciled Cost of Revenue": "88,203", "Reconciled Depreciation": "48,703", "Net Income from Continuing Operation Net Minority Interest": "2,626", "Total Unusual Items Excluding Goodwill": "-", "Total Unusual Items": "-", "Normalized EBITDA": "47,556", "Tax Rate for Calcs": "0", "Tax Effect of Unusual Items": "0"}, "12/31/2019": {"Duration": "12/31/2019", "Total Revenue": "633,906", "Cost of Revenue": "264,667", "Gross Profit": "369,239", "Operating Expense": "272,193", "Operating Income": "97,046", "Net Non Operating Interest Income Expense": "-29,468", "Other Income Expense": "3,461", "Pretax Income": "71,039", "Tax Provision": "16,104", "Net Income Common Stockholders": "54,935", "Diluted NI Available to Com Stockholders": "54,935", "Basic EPS": "1.10", "Diluted EPS": "1.10", "Basic Average Shares": "49,811", "Diluted Average Shares": "50,101", "Total Operating Income as Reported": "97,046", "Total Expenses": "536,860", "Net Income from Continuing & Discontinued Operation": "54,935", "Normalized Income": "54,935", "Interest Expense": "29,468", "Net Interest Income": "-29,468", "EBIT": "100,507", "EBITDA": "-", "Reconciled Cost of Revenue": "264,242", "Reconciled Depreciation": "160,078", "Net Income from Continuing Operation Net Minority Interest": "54,935", "Total Unusual Items Excluding Goodwill": "0", "Total Unusual Items": "0", "Normalized EBITDA": "260,585", "Tax Rate for Calcs": "0", "Tax Effect of Unusual Items": "0"}, "12/31/2018": {"Duration": "12/31/2018", "Total Revenue": "630,854", "Cost of Revenue": "257,981", "Gross Profit": "372,873", "Operating Expense": "279,627", "Operating Income": "93,246", "Net Non Operating Interest Income Expense": "-34,847", "Other Income Expense": "3,713", "Pretax Income": "62,112", "Tax Provision": "15,517", "Net Income Common Stockholders": "46,595", "Diluted NI Available to Com Stockholders": "46,595", "Basic EPS": "0.94", "Diluted EPS": "0.93", "Basic Average Shares": "49,542", "Diluted Average Shares": "50,063", "Total Operating Income as Reported": "93,246", "Total Expenses": "537,608", "Net Income from Continuing & Discontinued Operation": "46,595", "Normalized Income": "46,801", "Interest Expense": "34,847", "Net Interest Income": "-34,847", "EBIT": "96,959", "EBITDA": "-", "Reconciled Cost of Revenue": "257,981", "Reconciled Depreciation": "166,405", "Net Income from Continuing Operation Net Minority Interest": "46,595", "Total Unusual Items Excluding Goodwill": "-275", "Total Unusual Items": "-275", "Normalized EBITDA": "263,639", "Tax Rate for Calcs": "0", "Tax Effect of Unusual Items": "-68.75"}}, "bs": {"12/31/2020": {"Duration": "12/31/2020", "Total Assets": "2,031,707", "Total Liabilities Net Minority Interest": "1,449,313", "Total Equity Gross Minority Interest": "582,394", "Total Capitalization": "582,394", "Common Stock Equity": "582,394", "Capital Lease Obligations": "49,557", "Net Tangible Assets": "475,635", "Working Capital": "200,654", "Invested Capital": "1,270,857", "Tangible Book Value": "475,635", "Total Debt": "738,020", "Net Debt": "493,066", "Share Issued": "49,868", "Ordinary Shares Number": "49,868"}, "12/31/2019": {"Duration": "12/31/2019", "Total Assets": "1,860,691", "Total Liabilities Net Minority Interest": "1,391,269", "Total Equity Gross Minority Interest": "469,422", "Total Capitalization": "1,157,886", "Common Stock Equity": "469,422", "Capital Lease Obligations": "395,100", "Net Tangible Assets": "6,205", "Working Capital": "91,695", "Invested Capital": "1,189,536", "Tangible Book Value": "6,205", "Total Debt": "1,115,214", "Net Debt": "618,463", "Share Issued": "49,671", "Ordinary Shares Number": "49,671"}, "12/31/2018": {"Duration": "12/31/2018", "Total Assets": "1,484,766", "Total Liabilities Net Minority Interest": "1,042,519", "Total Equity Gross Minority Interest": "442,247", "Total Capitalization": "1,191,871", "Common Stock Equity": "442,247", "Capital Lease Obligations": "-", "Net Tangible Assets": "-70,279", "Working Capital": "121,663", "Invested Capital": "1,212,489", "Tangible Book Value": "-70,279", "Total Debt": "770,242", "Net Debt": "685,156", "Share Issued": "49,630", "Ordinary Shares Number": "49,630"}}, "cf": {"TTM": {"Duration": "TTM", "Operating Cash Flow": "302,867", "Investing Cash Flow": "-155,588", "Financing Cash Flow": "-53,533", "End Cash Position": "195,397", "Income Tax Paid Supplemental Data": "-", "Interest Paid Supplemental Data": "-", "Capital Expenditure": "-120,450", "Issuance of Capital Stock": "-", "Issuance of Debt": "-", "Repayment of Debt": "-", "Repurchase of Capital Stock": "0", "Free Cash Flow": "182,417"}, "12/31/2020": {"Duration": "12/31/2020", "Operating Cash Flow": "302,867", "Investing Cash Flow": "-155,588", "Financing Cash Flow": "-53,533", "End Cash Position": "195,397", "Income Tax Paid Supplemental Data": "-", "Interest Paid Supplemental Data": "-", "Capital Expenditure": "-120,450", "Issuance of Capital Stock": "-", "Issuance of Debt": "-", "Repayment of Debt": "-", "Repurchase of Capital Stock": "0", "Free Cash Flow": "182,417"}, "12/31/2019": {"Duration": "12/31/2019", "Operating Cash Flow": "259,145", "Investing Cash Flow": "-165,334", "Financing Cash Flow": "-77,246", "End Cash Position": "101,651", "Income Tax Paid Supplemental Data": "-", "Interest Paid Supplemental Data": "-", "Capital Expenditure": "-155,534", "Issuance of Capital Stock": "-", "Issuance of Debt": "0", "Repayment of Debt": "-53,197", "Repurchase of Capital Stock": "-7,231", "Free Cash Flow": "103,611"}, "12/31/2018": {"Duration": "12/31/2018", "Operating Cash Flow": "265,647", "Investing Cash Flow": "-187,800", "Financing Cash Flow": "-71,346", "End Cash Position": "85,086", "Income Tax Paid Supplemental Data": "-", "Interest Paid Supplemental Data": "33,034", "Capital Expenditure": "-136,641", "Issuance of Capital Stock": "0", "Issuance of Debt": "15,000", "Repayment of Debt": "-66,264", "Repurchase of Capital Stock": "-", "Free Cash Flow": "129,006"}}}}, {"CHT": {"quote": {"03/19/2021": {"value": "38.82", "Market Cap": "30.416B", "Beta (5Y Monthly)": "0.01", "PE Ratio (TTM)": "25.54", "EPS (TTM)": "1.52", "Earnings Date": "N/A", "Forward Dividend & Yield": "1.42 (3.65%)", "Ex-Dividend Date": "Jul 01, 2020", "1y Target Est": "37.63"}}, "fin": {"TTM": {"Duration": "TTM", "Total Revenue": "178,622,827", "Cost of Revenue": "117,206,244", "Gross Profit": "61,416,583", "Operating Expense": "23,491,213", "Operating Income": "37,925,370", "Net Non Operating Interest Income Expense": "-118,769", "Other Income Expense": "3,076,828", "Pretax Income": "40,883,429", "Tax Provision": "7,477,299", "Net Income Common Stockholders": "33,406,130", "Average Dilution Earnings": "-7,241", "Diluted NI Available to Com Stockholders": "33,398,889", "Basic EPS": "-", "Diluted EPS": "-", "Basic Average Shares": "-", "Diluted Average Shares": "-", "Total Operating Income as Reported": "39,539,657", "Total Expenses": "140,697,457", "Net Income from Continuing & Discontinued Operation": "33,406,130", "Normalized Income": "31,957,637", "Interest Income": "52,889", "Interest Expense": "171,658", "Net Interest Income": "-118,769", "EBIT": "41,055,087", "EBITDA": "76,243,376", "Reconciled Cost of Revenue": "117,206,244", "Reconciled Depreciation": "35,188,289", "Net Income from Continuing Operation Net Minority Interest": "33,406,130", "Total Unusual Items Excluding Goodwill": "1,772,710", "Total Unusual Items": "1,772,710", "Normalized EBITDA": "74,470,666", "Tax Rate for Calcs": "0", "Tax Effect of Unusual Items": "324,217"}, "12/31/2020": {"Duration": "12/31/2020", "Total Revenue": "178,622,827", "Cost of Revenue": "117,206,244", "Gross Profit": "61,416,583", "Operating Expense": "23,491,213", "Operating Income": "37,925,370", "Net Non Operating Interest Income Expense": "-118,769", "Other Income Expense": "3,076,828", "Pretax Income": "40,883,429", "Tax Provision": "7,477,299", "Net Income Common Stockholders": "33,406,130", "Average Dilution Earnings": "-7,241", "Diluted NI Available to Com Stockholders": "33,398,889", "Basic EPS": "-", "Diluted EPS": "-", "Basic Average Shares": "-", "Diluted Average Shares": "-", "Total Operating Income as Reported": "39,539,657", "Total Expenses": "140,697,457", "Net Income from Continuing & Discontinued Operation": "33,406,130", "Normalized Income": "31,957,637", "Interest Income": "52,889", "Interest Expense": "171,658", "Net Interest Income": "-118,769", "EBIT": "41,055,087", "EBITDA": "-", "Reconciled Cost of Revenue": "117,206,244", "Reconciled Depreciation": "35,188,289", "Net Income from Continuing Operation Net Minority Interest": "33,406,130", "Total Unusual Items Excluding Goodwill": "1,772,710", "Total Unusual Items": "1,772,710", "Normalized EBITDA": "74,470,666", "Tax Rate for Calcs": "0", "Tax Effect of Unusual Items": "324,217"}, "12/31/2019": {"Duration": "12/31/2019", "Total Revenue": "207,520,000", "Cost of Revenue": "135,953,000", "Gross Profit": "71,567,000", "Operating Expense": "30,794,000", "Operating Income": "40,773,000", "Net Non Operating Interest Income Expense": "147,000", "Other Income Expense": "947,000", "Pretax Income": "41,867,000", "Tax Provision": "7,946,000", "Net Income Common Stockholders": "32,947,000", "Average Dilution Earnings": "-4,000", "Diluted NI Available to Com Stockholders": "32,943,000", "Basic EPS": "42.30", "Diluted EPS": "42.20", "Basic Average Shares": "775,745", "Diluted Average Shares": "776,531", "Total Operating Income as Reported": "40,646,000", "Total Expenses": "166,747,000", "Net Income from Continuing & Discontinued Operation": "32,947,000", "Normalized Income": "32,702,380", "Interest Income": "251,000", "Interest Expense": "104,000", "Net Interest Income": "147,000", "EBIT": "41,971,000", "EBITDA": "-", "Reconciled Cost of Revenue": "135,953,000", "Reconciled Depreciation": "35,176,000", "Net Income from Continuing Operation Net Minority Interest": "32,947,000", "Total Unusual Items Excluding Goodwill": "302,000", "Total Unusual Items": "302,000", "Normalized EBITDA": "76,845,000", "Tax Rate for Calcs": "0", "Tax Effect of Unusual Items": "57,380"}, "12/31/2018": {"Duration": "12/31/2018", "Total Revenue": "215,483,000", "Cost of Revenue": "139,545,000", "Gross Profit": "75,938,000", "Operating Expense": "32,404,000", "Operating Income": "43,534,000", "Net Non Operating Interest Income Expense": "179,000", "Other Income Expense": "1,273,000", "Pretax Income": "44,986,000", "Tax Provision": "6,405,000", "Net Income Common Stockholders": "37,557,000", "Average Dilution Earnings": "-6,000", "Diluted NI Available to Com Stockholders": "37,551,000", "Basic EPS": "45.80", "Diluted EPS": "45.70", "Basic Average Shares": "775,745", "Diluted Average Shares": "776,651", "Total Operating Income as Reported": "43,644,000", "Total Expenses": "171,949,000", "Net Income from Continuing & Discontinued Operation": "37,557,000", "Normalized Income": "37,102,260", "Interest Income": "197,000", "Interest Expense": "18,000", "Net Interest Income": "179,000", "EBIT": "45,004,000", "EBITDA": "-", "Reconciled Cost of Revenue": "139,545,000", "Reconciled Depreciation": "31,868,000", "Net Income from Continuing Operation Net Minority Interest": "37,557,000", "Total Unusual Items Excluding Goodwill": "530,000", "Total Unusual Items": "530,000", "Normalized EBITDA": "76,342,000", "Tax Rate for Calcs": "0", "Tax Effect of Unusual Items": "75,260"}}, "bs": {"12/31/2020": {"Duration": "12/31/2020", "Total Assets": "484,339,022", "Total Liabilities Net Minority Interest": "106,408,006", "Total Equity Gross Minority Interest": "377,931,016", "Total Capitalization": "397,911,288", "Common Stock Equity": "377,931,016", "Capital Lease Obligations": "8,620,647", "Net Tangible Assets": "288,207,610", "Working Capital": "-8,431,127", "Invested Capital": "397,911,288", "Tangible Book Value": "288,207,610", "Total Debt": "28,600,919", "Share Issued": "7,757,447", "Ordinary Shares Number": "7,757,447"}, "12/31/2019": {"Duration": "12/31/2019", "Total Assets": "477,128,000", "Total Liabilities Net Minority Interest": "92,856,000", "Total Equity Gross Minority Interest": "384,272,000", "Total Capitalization": "375,757,000", "Common Stock Equity": "374,157,000", "Capital Lease Obligations": "9,758,000", "Net Tangible Assets": "327,110,000", "Working Capital": "27,929,000", "Invested Capital": "375,847,000", "Tangible Book Value": "327,110,000", "Total Debt": "11,448,000", "Share Issued": "7,757,447", "Ordinary Shares Number": "7,757,447"}, "12/31/2018": {"Duration": "12/31/2018", "Total Assets": "467,056,000", "Total Liabilities Net Minority Interest": "82,527,000", "Total Equity Gross Minority Interest": "384,529,000", "Total Capitalization": "376,272,000", "Common Stock Equity": "374,672,000", "Capital Lease Obligations": "-", "Net Tangible Assets": "323,728,000", "Working Capital": "28,471,000", "Invested Capital": "376,372,000", "Tangible Book Value": "323,728,000", "Total Debt": "1,700,000", "Share Issued": "7,757,447", "Ordinary Shares Number": "7,757,447"}}, "cf": {"TTM": {"Duration": "TTM", "Operating Cash Flow": "70,163,197", "Investing Cash Flow": "-66,481,394", "Financing Cash Flow": "-8,673,462", "End Cash Position": "20,090,053", "Capital Expenditure": "-70,280,211", "Issuance of Debt": "61,000,000", "Repayment of Debt": "-37,287,475", "Free Cash Flow": "-117,014"}, "12/31/2020": {"Duration": "12/31/2020", "Operating Cash Flow": "70,163,197", "Investing Cash Flow": "-66,481,394", "Financing Cash Flow": "-8,673,462", "End Cash Position": "20,090,053", "Capital Expenditure": "-70,280,211", "Issuance of Debt": "61,000,000", "Repayment of Debt": "-37,287,475", "Free Cash Flow": "-117,014"}, "12/31/2019": {"Duration": "12/31/2019", "Operating Cash Flow": "72,427,000", "Investing Cash Flow": "-27,127,000", "Financing Cash Flow": "-38,934,000", "End Cash Position": "34,050,000", "Capital Expenditure": "-24,529,000", "Issuance of Debt": "575,000", "Repayment of Debt": "-4,313,000", "Free Cash Flow": "47,898,000"}, "12/31/2018": {"Duration": "12/31/2018", "Operating Cash Flow": "66,366,000", "Investing Cash Flow": "-32,614,000", "Financing Cash Flow": "-35,035,000", "End Cash Position": "27,645,000", "Capital Expenditure": "-29,048,000", "Issuance of Debt": "360,000", "Repayment of Debt": "-330,000", "Free Cash Flow": "37,318,000"}}}}, {"INVT": {"quote": {"03/19/2021": {"value": "0.0326", "Market Cap": "572,430", "Beta (5Y Monthly)": "1.51", "PE Ratio (TTM)": "0.04", "EPS (TTM)": "0.7800", "Earnings Date": "N/A", "Forward Dividend & Yield": "N/A (N/A)", "Ex-Dividend Date": "Jun 09, 2014", "1y Target Est": "10.30"}}, "fin": {}, "bs": {}, "cf": {}}}, {"OTEL": {"quote": {"03/19/2021": {"value": "11.53", "Market Cap": "39.453M", "Beta (5Y Monthly)": "1.65", "PE Ratio (TTM)": "6.30", "EPS (TTM)": "1.83", "Earnings Date": "May 03, 2021 - May 07, 2021", "Forward Dividend & Yield": "N/A (N/A)", "Ex-Dividend Date": "N/A", "1y Target Est": "N/A"}}, "fin": {"TTM": {"Duration": "TTM", "Total Revenue": "62,433", "Cost of Revenue": "29,997", "Gross Profit": "32,436", "Operating Expense": "18,050", "Operating Income": "14,386", "Net Non Operating Interest Income Expense": "-5,086", "Other Income Expense": "729", "Pretax Income": "10,029", "Tax Provision": "2,296", "Net Income Common Stockholders": "7,733", "Diluted NI Available to Com Stockholders": "7,733", "Basic EPS": "-", "Diluted EPS": "-", "Basic Average Shares": "-", "Diluted Average Shares": "-", "Total Operating Income as Reported": "14,386", "Total Expenses": "48,047", "Net Income from Continuing & Discontinued Operation": "7,733", "Normalized Income": "7,733", "Interest Expense": "5,086", "Net Interest Income": "-5,086", "EBIT": "15,115", "EBITDA": "22,863", "Reconciled Cost of Revenue": "29,997", "Reconciled Depreciation": "7,748", "Net Income from Continuing Operation Net Minority Interest": "7,733", "Total Unusual Items Excluding Goodwill": "-", "Total Unusual Items": "-", "Normalized EBITDA": "22,863", "Tax Rate for Calcs": "0", "Tax Effect of Unusual Items": "0"}, "12/31/2020": {"Duration": "12/31/2020", "Total Revenue": "61,971", "Cost of Revenue": "30,251", "Gross Profit": "31,720", "Operating Expense": "20,178", "Operating Income": "11,542", "Net Non Operating Interest Income Expense": "-4,025", "Other Income Expense": "820", "Pretax Income": "8,337", "Tax Provision": "2,030", "Net Income Common Stockholders": "6,307", "Diluted NI Available to Com Stockholders": "6,307", "Basic EPS": "1.84", "Diluted EPS": "1.83", "Basic Average Shares": "3,422", "Diluted Average Shares": "3,441", "Total Operating Income as Reported": "11,542", "Total Expenses": "50,429", "Net Income from Continuing & Discontinued Operation": "6,307", "Normalized Income": "6,307", "Interest Expense": "4,025", "Net Interest Income": "-4,025", "EBIT": "12,362", "EBITDA": "-", "Reconciled Cost of Revenue": "30,251", "Reconciled Depreciation": "8,309", "Net Income from Continuing Operation Net Minority Interest": "6,307", "Total Unusual Items Excluding Goodwill": "-", "Total Unusual Items": "-", "Normalized EBITDA": "20,671", "Tax Rate for Calcs": "0", "Tax Effect of Unusual Items": "0"}, "12/31/2019": {"Duration": "12/31/2019", "Total Revenue": "62,766", "Cost of Revenue": "30,075", "Gross Profit": "32,691", "Operating Expense": "17,847", "Operating Income": "14,844", "Net Non Operating Interest Income Expense": "-5,271", "Other Income Expense": "616", "Pretax Income": "10,189", "Tax Provision": "2,393", "Net Income Common Stockholders": "7,796", "Diluted NI Available to Com Stockholders": "7,796", "Basic EPS": "2.28", "Diluted EPS": "2.27", "Basic Average Shares": "3,413", "Diluted Average Shares": "3,430", "Total Operating Income as Reported": "14,844", "Total Expenses": "47,922", "Net Income from Continuing & Discontinued Operation": "7,796", "Normalized Income": "7,796", "Interest Expense": "5,271", "Net Interest Income": "-5,271", "EBIT": "15,460", "EBITDA": "-", "Reconciled Cost of Revenue": "30,075", "Reconciled Depreciation": "7,643", "Net Income from Continuing Operation Net Minority Interest": "7,796", "Total Unusual Items Excluding Goodwill": "0", "Total Unusual Items": "0", "Normalized EBITDA": "23,103", "Tax Rate for Calcs": "0", "Tax Effect of Unusual Items": "0"}, "12/31/2018": {"Duration": "12/31/2018", "Total Revenue": "66,068", "Cost of Revenue": "30,592", "Gross Profit": "35,476", "Operating Expense": "17,683", "Operating Income": "17,793", "Net Non Operating Interest Income Expense": "-5,844", "Other Income Expense": "263", "Pretax Income": "12,212", "Tax Provision": "2,745", "Net Income Common Stockholders": "9,467", "Diluted NI Available to Com Stockholders": "9,467", "Basic EPS": "2.79", "Diluted EPS": "2.76", "Basic Average Shares": "3,389", "Diluted Average Shares": "3,435", "Total Operating Income as Reported": "17,793", "Total Expenses": "48,275", "Net Income from Continuing & Discontinued Operation": "9,467", "Normalized Income": "9,467", "Interest Expense": "5,844", "Net Interest Income": "-5,844", "EBIT": "18,056", "EBITDA": "-", "Reconciled Cost of Revenue": "30,592", "Reconciled Depreciation": "7,232", "Net Income from Continuing Operation Net Minority Interest": "9,467", "Total Unusual Items Excluding Goodwill": "0", "Total Unusual Items": "0", "Normalized EBITDA": "25,288", "Tax Rate for Calcs": "0", "Tax Effect of Unusual Items": "0"}}, "bs": {"12/31/2020": {"Duration": "12/31/2020", "Total Assets": "127,404", "Total Liabilities Net Minority Interest": "102,149", "Total Equity Gross Minority Interest": "25,255", "Total Capitalization": "86,324", "Common Stock Equity": "25,255", "Capital Lease Obligations": "1,539", "Net Tangible Assets": "-19,879", "Working Capital": "3,607", "Invested Capital": "93,270", "Tangible Book Value": "-19,879", "Total Debt": "69,554", "Net Debt": "59,570", "Share Issued": "3,422", "Ordinary Shares Number": "3,422"}, "12/31/2019": {"Duration": "12/31/2019", "Total Assets": "120,745", "Total Liabilities Net Minority Interest": "101,985", "Total Equity Gross Minority Interest": "18,760", "Total Capitalization": "83,932", "Common Stock Equity": "18,760", "Capital Lease Obligations": "1,146", "Net Tangible Assets": "-26,746", "Working Capital": "2,482", "Invested Capital": "87,861", "Tangible Book Value": "-26,746", "Total Debt": "70,247", "Net Debt": "65,988", "Share Issued": "3,413", "Ordinary Shares Number": "3,413"}, "12/31/2018": {"Duration": "12/31/2018", "Total Assets": "114,352", "Total Liabilities Net Minority Interest": "103,450", "Total Equity Gross Minority Interest": "10,902", "Total Capitalization": "80,009", "Common Stock Equity": "10,902", "Capital Lease Obligations": "-", "Net Tangible Assets": "-34,993", "Working Capital": "2,788", "Invested Capital": "83,913", "Tangible Book Value": "-34,993", "Total Debt": "73,011", "Net Debt": "68,354", "Share Issued": "3,389", "Ordinary Shares Number": "3,389"}}, "cf": {"TTM": {"Duration": "TTM", "Operating Cash Flow": "17,389", "Investing Cash Flow": "-14,146", "Financing Cash Flow": "-4,593", "End Cash Position": "4,128", "Income Tax Paid Supplemental Data": "807", "Interest Paid Supplemental Data": "4,650", "Capital Expenditure": "-14,275", "Issuance of Capital Stock": "0", "Issuance of Debt": "2,975", "Repayment of Debt": "-4,350", "Free Cash Flow": "3,114"}, "12/31/2020": {"Duration": "12/31/2020", "Operating Cash Flow": "16,745", "Investing Cash Flow": "-9,805", "Financing Cash Flow": "-1,608", "End Cash Position": "8,445", "Income Tax Paid Supplemental Data": "884", "Interest Paid Supplemental Data": "3,502", "Capital Expenditure": "-10,036", "Issuance of Capital Stock": "0", "Issuance of Debt": "2,975", "Repayment of Debt": "-4,350", "Free Cash Flow": "6,709"}, "12/31/2019": {"Duration": "12/31/2019", "Operating Cash Flow": "15,450", "Investing Cash Flow": "-12,444", "Financing Cash Flow": "-4,550", "End Cash Position": "3,113", "Income Tax Paid Supplemental Data": "1,993", "Interest Paid Supplemental Data": "4,834", "Capital Expenditure": "-12,440", "Issuance of Capital Stock": "0", "Issuance of Debt": "0", "Repayment of Debt": "-4,350", "Free Cash Flow": "3,010"}, "12/31/2018": {"Duration": "12/31/2018", "Operating Cash Flow": "20,760", "Investing Cash Flow": "-7,994", "Financing Cash Flow": "-11,679", "End Cash Position": "4,657", "Income Tax Paid Supplemental Data": "502", "Interest Paid Supplemental Data": "5,383", "Capital Expenditure": "-7,983", "Issuance of Capital Stock": "-", "Issuance of Debt": "0", "Repayment of Debt": "-11,350", "Free Cash Flow": "12,777"}}}}, {"IMTO": {"quote": {"03/19/2021": {"value": "0.0900", "Market Cap": "7.731M", "Beta (5Y Monthly)": "10.20", "PE Ratio (TTM)": "N/A", "EPS (TTM)": "-0.0210", "Earnings Date": "N/A", "Forward Dividend & Yield": "N/A (N/A)", "Ex-Dividend Date": "N/A", "1y Target Est": "N/A"}}, "fin": {}, "bs": {}, "cf": {}}}, {"SGRB": {"quote": {"03/19/2021": {"value": "0.1508", "Market Cap": "86,534", "Beta (5Y Monthly)": "0.21", "PE Ratio (TTM)": "N/A", "EPS (TTM)": "-0.2700", "Earnings Date": "N/A", "Forward Dividend & Yield": "N/A (N/A)", "Ex-Dividend Date": "N/A", "1y Target Est": "N/A"}}, "fin": {}, "bs": {}, "cf": {}}}, {"FTR": {"fin": {}, "bs": {}, "cf": {}}}, {"CTL": {"fin": {}, "bs": {}, "cf": {}}}, {"CEL": {"fin": {}, "bs": {}, "cf": {}}}, {"WIN": {"fin": {}, "bs": {}, "cf": {}}}]